cdm_tools/__init__.py
cdm_tools/core/__init__.py
cdm_tools/core/calendar.py
cdm_tools/core/filter.py
cdm_tools/core/join.py
cdm_tools/core/mapper.py
cdm_tools/core/normalize.py
cdm_tools/core/order.py
cdm_tools/core/read.py
cdm_tools/core/select.py
cdm_tools/core/summarize.py
cdm_tools/core/write.py
cdm_tools/models/__init__.py
cdm_tools/models/common.py
cdm_tools/models/detect.py
cdm_tools/models/formats.py
cdm_tools/models/helpers.py
cdm_tools/models/review.py
cdm_tools/models/transform.py
cdm_tools/models/types.py
cdm_tools/models/validate.py
cdm_tools/models/templates/__init__.py
cdm_tools/models/templates/journal_entry_testing/__init__.py
cdm_tools/models/templates/journal_entry_testing/analytic.py
cdm_tools/models/templates/journal_entry_testing/chart_of_accounts.py
cdm_tools/models/templates/journal_entry_testing/fiscal_calendar.py
cdm_tools/models/templates/journal_entry_testing/general_ledger_detail.py
cdm_tools/models/templates/journal_entry_testing/trial_balance.py
cdm_tools/tidy/__init__.py
cdm_tools/tidy/tidydataframe/__init__.py
cdm_tools/tidy/tidydataframe/tidydataframe.py
cdm_tools/tidy/tidyworkflow/__init__.py
cdm_tools/tidy/tidyworkflow/tidyworkflow.py
cdm_tools-0.1.0.dist-info/METADATA
cdm_tools-0.1.0.dist-info/WHEEL
cdm_tools-0.1.0.dist-info/top_level.txt
cdm_tools-0.1.0.dist-info/RECORD
