Metadata-Version: 2.1
Name: cdm-tools
Version: 0.1.0
Summary: Add your description here
Requires-Python: >=3.10
Requires-Dist: attrs >=24.2.0
Requires-Dist: loguru >=0.7.2
Requires-Dist: pydantic >=2.9.2
Requires-Dist: pyspark >=3.5.3
